django_plans_paypal-1.1.0.dist-info/licenses/AUTHORS.rst
django_plans_paypal-1.1.0.dist-info/licenses/LICENSE
plans_paypal/__init__.py
plans_paypal/admin.py
plans_paypal/apps.py
plans_paypal/hooks.py
plans_paypal/models.py
plans_paypal/urls.py
plans_paypal/views.py
plans_paypal/migrations/0001_initial.py
plans_paypal/migrations/0002_auto_20211130_1117.py
plans_paypal/migrations/0003_recurringuserplan_renewal_triggered_by_task_to_other.py
plans_paypal/migrations/__init__.py
plans_paypal/templates/paypal_payments/payment.html
plans_paypal/tests/__init__.py
plans_paypal/tests/test_hooks.py
plans_paypal/tests/test_views.py
tests/__init__.py
tests/settings.py
tests/urls.py
tests/templates/base.html
django_plans_paypal-1.1.0.dist-info/METADATA
django_plans_paypal-1.1.0.dist-info/WHEEL
django_plans_paypal-1.1.0.dist-info/top_level.txt
django_plans_paypal-1.1.0.dist-info/RECORD
