Metadata-Version: 2.4
Name: django-plans-paypal
Version: 1.1.0
Summary: Integration between django-plans and django-paypal.
Home-page: https://github.com/PetrDlouhy/django-plans-paypal
Author: Petr Dlouhý
Author-email: petr.dlouhy@email.cz
License: MIT
Keywords: django-plans-paypal
Classifier: Development Status :: 3 - Alpha
Classifier: Framework :: Django :: 1.11
Classifier: Framework :: Django :: 2.0
Classifier: Intended Audience :: Developers
Classifier: Natural Language :: English
Classifier: Programming Language :: Python :: 3
Classifier: Programming Language :: Python :: 3.4
Classifier: Programming Language :: Python :: 3.5
Classifier: Programming Language :: Python :: 3.6
License-File: LICENSE
License-File: AUTHORS.rst
Requires-Dist: django-author>=1.0.3
Requires-Dist: django-extensions
Requires-Dist: django-plans
Requires-Dist: django-paypal
Requires-Dist: django-related-admin
Dynamic: author
Dynamic: author-email
Dynamic: classifier
Dynamic: description
Dynamic: home-page
Dynamic: keywords
Dynamic: license
Dynamic: license-file
Dynamic: requires-dist
Dynamic: summary
